capgains/__init__.py
capgains/cli.py
capgains/commands/capgains_calc.py
capgains/commands/capgains_show.py
capgains/exchange_rate.py
capgains/ticker_gains.py
capgains/transaction.py
capgains/transactions.py
capgains/transactions_reader.py
cad_capgains-2.0.2.dist-info/LICENSE
cad_capgains-2.0.2.dist-info/METADATA
cad_capgains-2.0.2.dist-info/WHEEL
cad_capgains-2.0.2.dist-info/entry_points.txt
cad_capgains-2.0.2.dist-info/RECORD
