Metadata-Version: 2.1
Name: cad-capgains
Version: 2.0.2
Summary: A CLI tool to calculate your capital gains
Home-page: https://github.com/EmilMaric/cad-capital-gains
License: MIT
Keywords: capital,gains,canadian,tax
Author: Eddy Maric
Maintainer: Eddy Maric
Requires-Python: >=3.8,<4.0
Classifier: Development Status :: 5 - Production/Stable
Classifier: Environment :: Console
Classifier: Intended Audience :: End Users/Desktop
Classifier: License :: OSI Approved :: MIT License
Classifier: Operating System :: OS Independent
Classifier: Programming Language :: Python :: 3
Classifier: Programming Language :: Python :: 3.8
Classifier: Programming Language :: Python :: 3.9
Classifier: Programming Language :: Python :: 3.10
Classifier: Programming Language :: Python :: 3.11
Classifier: Programming Language :: Python :: 3.12
Classifier: Topic :: Office/Business :: Financial :: Accounting
Requires-Dist: click (>=7.1.2,<8.0.0)
Requires-Dist: requests (>=2.23.0,<3.0.0)
Requires-Dist: tabulate (>=0.8.7,<0.9.0)
Project-URL: Repository, https://github.com/EmilMaric/cad-capital-gains
